tpp_guille_santi_commons/__init__.py
tpp_guille_santi_commons/entities.py
tpp_guille_santi_commons-0.0.3.dist-info/LICENSE
tpp_guille_santi_commons-0.0.3.dist-info/METADATA
tpp_guille_santi_commons-0.0.3.dist-info/WHEEL
tpp_guille_santi_commons-0.0.3.dist-info/top_level.txt
tpp_guille_santi_commons-0.0.3.dist-info/RECORD
