Metadata-Version: 2.1
Name: tpp-guille-santi-commons
Version: 0.0.3
Summary: Comons package for our TPP
Home-page: https://github.com/tpp-guille-santi/commons
Author: Santiago Gandolfo
Author-email: sgandolfo@fi.uba.ar
Project-URL: Bug Tracker, https://github.com/tpp-guille-santi/commons/issues
Classifier: Programming Language :: Python :: 3
Classifier: License :: OSI Approved :: MIT License
Classifier: Operating System :: OS Independent
Requires-Python: >=3.6
License-File: LICENSE
